wreqs/__init__.py
wreqs/context.py
wreqs/error.py
wreqs/fmt.py
wreqs/py.typed
wreqs-1.2.1.dist-info/LICENSE
wreqs-1.2.1.dist-info/METADATA
wreqs-1.2.1.dist-info/WHEEL
wreqs-1.2.1.dist-info/top_level.txt
wreqs-1.2.1.dist-info/RECORD
