Metadata-Version: 2.1
Name: wreqs
Version: 1.2.1
Summary: Simplified and enhanced request handling.
Home-page: https://github.com/munozarturo/wreqs
Author: Arturo Munoz
Author-email: munoz.arturoroman@gmail.com
Project-URL: Bug Reports, https://github.com/munozarturo/wreqs/issues
Project-URL: Source, https://github.com/munozarturo/wreqs/
Keywords: http,requests,wrapper,retry,timeout
Classifier: Intended Audience :: Developers
Classifier: License :: OSI Approved :: MIT License
Classifier: Programming Language :: Python :: 3
Classifier: Programming Language :: Python :: 3.10
Classifier: Programming Language :: Python :: 3.11
Classifier: Programming Language :: Python :: 3.12
Classifier: Operating System :: OS Independent
Classifier: Topic :: Software Development :: Libraries :: Python Modules
Classifier: Topic :: Internet :: WWW/HTTP
Requires-Python: >=3.7
License-File: LICENSE
Requires-Dist: requests >=2.20.0
Provides-Extra: dev
Requires-Dist: pytest ; extra == 'dev'
Requires-Dist: pytest-cov ; extra == 'dev'
Requires-Dist: flask ; extra == 'dev'
Requires-Dist: mypy ; extra == 'dev'
Requires-Dist: flake8 ; extra == 'dev'
Requires-Dist: black ; extra == 'dev'
Provides-Extra: docs
Requires-Dist: sphinx ; extra == 'docs'
Requires-Dist: sphinx-rtd-theme ; extra == 'docs'
